Metadata-Version: 1.0
Name: webmoney-api
Version: 0.0.10
Summary: Wrapper for webmoney interfaces (https://wiki.webmoney.ru/projects/webmoney/wiki/WM-API)
Home-page: https://bitbucket.org/sallyruthstruik/python-webmoney-api
Author: Stas Kaledin
Author-email: staskaledin@gmail.com
License: UNKNOWN
Platform: UNKNOWN
